topsis_harshleen_102303220/_init_.py
topsis_harshleen_102303220/topsis.py
topsis_harshleen_102303220-0.1.2.dist-info/METADATA
topsis_harshleen_102303220-0.1.2.dist-info/WHEEL
topsis_harshleen_102303220-0.1.2.dist-info/entry_points.txt
topsis_harshleen_102303220-0.1.2.dist-info/top_level.txt
topsis_harshleen_102303220-0.1.2.dist-info/RECORD
