Metadata-Version: 2.4
Name: topsis-harshleen-102303220
Version: 0.1.2
Summary: TOPSIS command-line tool for multi-criteria decision making
Author-email: Harshleen <harshleenkaur781@gmail.com>
License: MIT
Project-URL: Homepage, https://pypi.org/project/topsis-harshleen-102303220/
Keywords: topsis,multi-criteria,decision-making
Requires-Python: >=3.8
